poetry_demo1507/__init__.py
poetry_demo1507/main.py
poetry_demo1507-0.1.1.dist-info/entry_points.txt
poetry_demo1507-0.1.1.dist-info/WHEEL
poetry_demo1507-0.1.1.dist-info/METADATA
poetry_demo1507-0.1.1.dist-info/RECORD
